bubbleproc-1.0.4.dist-info/METADATA
bubbleproc-1.0.4.dist-info/WHEEL
bubbleproc/__init__.py
bubbleproc/_sandbox.py
bubbleproc/_bubbleproc_rs.cpython-313-x86_64-linux-gnu.so
bubbleproc-1.0.4.dist-info/RECORD
