Metadata-Version: 2.4
Name: bubbleproc
Version: 1.0.4
Classifier: Development Status :: 4 - Beta
Classifier: Intended Audience :: Developers
Classifier: License :: OSI Approved :: MIT License
Classifier: Operating System :: POSIX :: Linux
Classifier: Programming Language :: Python :: 3
Classifier: Programming Language :: Rust
Summary: Bubblewrap sandboxing for Python
License: MIT
Requires-Python: >=3.8
